[
    {   "id": 1,
        "nombre": "Venta al Público",
        "apellido_paterno": "",
        "apellido_materno": "",
        "genero": "",
        "rfc": "",
        "curp": "",
        "telefono": "",
        "correo_electronico": "",
        "numero_unico_cliente": "",
        "estatus": "Activo",
        "fecha_nacimiento": "",
        "domicilio": "Calle 123",
        "codigo_postal": "12345",
        "ciudad": "León",
        "estado": "Guanajuato",
        "colonia": "Futurama Monterrey"
    },
    {   "id": 2,
        "numero_unico_cliente": "2",
        "nombre": "Ana Karla",
        "apellido_paterno": "Gutierrez",
        "apellido_materno": "Ramirez",
        "genero": "Femenino",
        "fecha_nacimiento": "1992-12-05",
        "rfc": "GUAA921205987",
        "curp": "GUAA921205MDFTRN04",
        "correo_electronico": "ana@example.com'",
        "telefono": "4773002134",
        "fecha_ingreso": "2023-08-06",
        "domicilio": "Av. Central 321",
        "colonia": "Juarez",
        "codigo_postal": "54321",
        "estatus": "Activo",
        "ciudad": "León",
        "estado": "Guanajuato"
    },
    {   "id": 3,
        "numero_unico_cliente": "3",
        "nombre": "Juan Carlos",
        "apellido_paterno": "Martinez",
        "apellido_materno": "Hernandez",
        "genero": "Masculino",
        "fecha_nacimiento": "1998-07-20",
        "rfc": "MAEC980720456",
        "curp": "MAEC980720HDFRTL05",
        "correo_electronico": "carlos@example.com",
        "telefono": "4774301243",
        "fecha_ingreso": "2023-08-06",
        "domicilio": "Calle 456",
        "colonia": "Reforma",
        "codigo_postal": "54321",
        "ciudad": "León",
        "estado": "Guanajuato",
        "estatus": "Activo"
    }
    ,
    {   "id": 4,
        "numero_unico_cliente": "3",
        "nombre": "Laura",
        "apellido_paterno": "Gonzalez",
        "apellido_materno": "García",
        "genero": "Femenino",
        "fecha_nacimiento": "1989-11-12",
        "rfc": "GOAL891112789",
        "curp": "GOAL891112MDFGNN06",
        "correo_electronico": "laura@example.com",
        "telefono": "4774502215",
        "fecha_ingreso": "2023-08-06",
        "domicilio": "Av. Independencia 789",
        "colonia": "Chapultepec",
        "codigo_postal": "98765",
        "ciudad": "León",
        "estado": "Guanajuato",
        "estatus": "Activo"
    }
    ,
    {   "id": 5,
        "numero_unico_cliente": "3",
        "nombre": "Javier José",
        "apellido_paterno": "Sanchez",
        "apellido_materno": "Duran",
        "genero": "Masculino",
        "fecha_nacimiento": "1994-03-25",
        "rfc": "MAEC980720456",
        "curp": "MAEC980720HDFRTL05",
        "correo_electronico": "carlos@example.com",
        "telefono": "4774301243",
        "fecha_ingreso": "2023-08-06",
        "domicilio": "Calle 987",
        "colonia": "La Paz",
        "codigo_postal": "12345",
        "ciudad": "León",
        "estado": "Guanajuato",
        "estatus": "Activo"
    },
    {   "id": 6,
        "numero_unico_cliente": "4",
        "nombre": "Sofia Lucia",
        "apellido_paterno": "Torres",
        "apellido_materno": "Perez",
        "genero": "Femenino",
        "fecha_nacimiento": "1991-08-28",
        "rfc": "TOSF910828456",
        "curp": "TOSF910828MDFRRR08",
        "correo_electronico": "sofia@example.com",
        "telefono": "4779082167",
        "fecha_ingreso": "2023-08-06",
        "domicilio": "Av. Revolución 654",
        "colonia": "San Pedro",
        "codigo_postal": "6789",
        "ciudad": "León",
        "estado": "Guanajuato",
        "estatus": "Activo"
    },
    {   "id": 7,
        "numero_unico_cliente": "5",
        "nombre": "Raul Fernando",
        "apellido_paterno": "Hernandez",
        "apellido_materno": "Ruiz",
        "genero": "Masculino",
        "fecha_nacimiento": "1997-06-14",
        "rfc": "HERR970614789",
        "curp": "HERR970614HDFLRL09",
        "correo_electronico": "raul@example.com",
        "telefono": "47778301245",
        "fecha_ingreso": "2023-08-06",
        "domicilio": "Calle 741",
        "colonia": "Roma",
        "codigo_postal": "11111",
        "ciudad": "León",
        "estado": "Guanajuato",
        "estatus": "Activo"
    },
    {   "id": 8,
        "numero_unico_cliente": "6",
        "nombre": "Paula Elena",
        "apellido_paterno": "Ramirez",
        "apellido_materno": "Mendez",
        "genero": "Femenino",
        "fecha_nacimiento": "1993-04-17",
        "rfc": "RAEE930417456",
        "curp": "RAEE930417HDFMRN10",
        "correo_electronico": "elena@example.com",
        "telefono": "4772138967",
        "fecha_ingreso": "2023-08-06",
        "domicilio":"Av. Hidalgo 852",
        "colonia": "Del Valle",
        "codigo_postal": "22222",
        "ciudad": "León",
        "estado": "Guanajuato",
        "estatus": "Activo"
    },
    {   "id": 9,
        "numero_unico_cliente": "7",
        "nombre": "María",
        "apellido_paterno": "López",
        "apellido_materno": "Hernández",
        "genero": "Femenino",
        "fecha_nacimiento": "1995-02-02",
        "rfc": "LOHM950202456",
        "curp": "LOHM950202MDFYYY13",
        "correo_electronico": "maria@example.com",
        "telefono": "4773215434",
        "fecha_ingreso": "2023-08-06",
        "domicilio":"San Jorgue del Maguey 114A",
        "colonia": "Azul Maguey",
        "codigo_postal": "22222",
        "ciudad": "León",
        "estado": "Guanajuato",
        "estatus": "Activo"
    },
    {   "id": 10,
        "numero_unico_cliente": "8",
        "nombre": "Fernando",
        "apellido_paterno": "García",
        "apellido_materno": "Martínez",
        "genero": "Masculino",
        "fecha_nacimiento": "1999-03-03",
        "rfc": "GAMC990303789",
        "curp": "GAMC990303HDFZZZ14",
        "correo_electronico": "carlos2@example.com",
        "telefono": "4775632134",
        "fecha_ingreso": "2023-08-06",
        "domicilio": "Calle 55",
        "colonia": "Col. Santa Fe",
        "codigo_postal": "55555",
        "ciudad": "León",
        "estado": "Guanajuato",
        "estatus": "Activo"
    }
]